vault_dump/__init__.py
vault_dump/main.py
vault_dump-0.0.4.dist-info/LICENSE
vault_dump-0.0.4.dist-info/METADATA
vault_dump-0.0.4.dist-info/WHEEL
vault_dump-0.0.4.dist-info/entry_points.txt
vault_dump-0.0.4.dist-info/top_level.txt
vault_dump-0.0.4.dist-info/RECORD
