Metadata-Version: 2.1
Name: vault-dump
Version: 0.0.4
Summary: A package to dump the configuration settings for a running hashicorp vault instance
Home-page: https://github.com/danielpops/vault-dump
Author: Daniel Popescu
Author-email: danielpops@gmail.com
Classifier: Programming Language :: Python :: 3.7
License-File: LICENSE
Requires-Dist: requests
